LICENSE
README.md
blackdark_nautobot_secrets_providers/__init__.py
blackdark_nautobot_secrets_providers/migrations/__init__.py
blackdark_nautobot_secrets_providers/providers/__init__.py
blackdark_nautobot_secrets_providers/providers/aws.py
blackdark_nautobot_secrets_providers/providers/aws_ssm.py
blackdark_nautobot_secrets_providers/providers/choices.py
blackdark_nautobot_secrets_providers/providers/delinea.py
blackdark_nautobot_secrets_providers/providers/hashicorp.py
blackdark_nautobot_secrets_providers/secrets.py
blackdark_nautobot_secrets_providers/template_content.py
blackdark_nautobot_secrets_providers/templates/blackdark_nautobot_secrets_providers/home.html
blackdark_nautobot_secrets_providers/templates/blackdark_nautobot_secrets_providers/tab_secret_detail_check.html
blackdark_nautobot_secrets_providers/tests/__init__.py
blackdark_nautobot_secrets_providers/tests/nautobot_config.py
blackdark_nautobot_secrets_providers/tests/test_basic.py
blackdark_nautobot_secrets_providers/tests/test_providers.py
blackdark_nautobot_secrets_providers/urls.py
blackdark_nautobot_secrets_providers/views.py
blackdark_nautobot_secrets_providers-1.10.0.dist-info/LICENSE
blackdark_nautobot_secrets_providers-1.10.0.dist-info/METADATA
blackdark_nautobot_secrets_providers-1.10.0.dist-info/WHEEL
blackdark_nautobot_secrets_providers-1.10.0.dist-info/RECORD
