Metadata-Version: 2.1
Name: blackdark-nautobot-secrets-providers
Version: 1.10.0
Summary: Nautobot Secrets Providers Plugin.
Home-page: https://github.com/nautobot/nautobot-plugin-secrets-providers
License: Apache-2.0
Keywords: nautobot,nautobot-plugin
Author: Network to Code, LLC
Author-email: opensource@networktocode.com
Requires-Python: >=3.7,<4.0
Classifier: License :: OSI Approved :: Apache Software License
Classifier: Programming Language :: Python :: 3
Classifier: Programming Language :: Python :: 3.7
Classifier: Programming Language :: Python :: 3.8
Classifier: Programming Language :: Python :: 3.9
Classifier: Programming Language :: Python :: 3.10
Classifier: Programming Language :: Python :: 3.11
Provides-Extra: all
Provides-Extra: aws
Provides-Extra: hashicorp
Provides-Extra: nautobot
Provides-Extra: thycotic
Requires-Dist: boto3 (>=1.19.5,<1.20.0) ; extra == "all" or extra == "aws"
Requires-Dist: hvac (>=0.11.0,<1.1.0) ; extra == "all" or extra == "hashicorp"
Requires-Dist: nautobot (>=1.2.1,<1.3.0) ; extra == "nautobot"
Requires-Dist: python-tss-sdk (>=1.2.0,<1.3.0) ; extra == "all" or extra == "thycotic"
Project-URL: Repository, https://github.com/nautobot/nautobot-plugin-secrets-providers
